gping.py
setup.py
gping.egg-info/PKG-INFO
gping.egg-info/SOURCES.txt
gping.egg-info/dependency_links.txt
gping.egg-info/requires.txt
gping.egg-info/top_level.txt