Metadata-Version: 1.1
Name: gping
Version: 0.1
Summary: A gevent fork of python-ping.
Home-page: https://github.com/mastahyeti/gping
Author: Ben Toews
Author-email: mastahyeti@gmail.com
License: UNKNOWN
Keywords: ping icmp network latency gevent
Platform: UNKNOWN
Requires: gevent
